lb2ticket/__init__.py
lb2ticket/core.py
lb2ticket/decrypt_utils.py
lb2ticket/model/base_model.py
lb2ticket/model/comment.py
lb2ticket/model/task.py
lb2ticket/model/ticket.py
lb2ticket/service/api_service.py
lb2ticket/service/task_service.py
lb2ticket/service/ticket_service.py
lb2ticket-0.2.7.dist-info/licenses/LICENCE.txt
lb2ticket-0.2.7.dist-info/METADATA
lb2ticket-0.2.7.dist-info/WHEEL
lb2ticket-0.2.7.dist-info/top_level.txt
lb2ticket-0.2.7.dist-info/RECORD
