Metadata-Version: 2.4
Name: lb2ticket
Version: 0.2.7
Summary: Framework da LB2 de gerenciamento de abertura de chamados no Workestre.
Author-email: Bruno Teruya <bruno.teruya@lb2.com.br>
License: MIT
Project-URL: Homepage, https://gitlab.com/lb2workestra/lb2ticket
Project-URL: Repository, https://gitlab.com/lb2workestra/lb2ticket
Project-URL: Bug Tracker, https://gitlab.com/lb2workestra/lb2ticket
Requires-Python: >=3.8
License-File: LICENCE.txt
Requires-Dist: requests>=2.25.0
Requires-Dist: pycryptodome
Dynamic: license-file
